{
    "title": "Location details    ",
    "type": "array",
    "format": "table",
    "uniqueItems": true,
    "items": {
        "type": "object",
        "properties": {
            "property": {
                "type": "string",
                "title": "Key",
                "enum": [
                    "depth",
                    "colour",
                    "fish"
                ]
            },
            "value": {
                "type": "string",
                "title": "Value"
            }
        }
    }
}